st_user_state/__init__.py
st_user_state/init_user_state.py
st_user_state/manager.py
st_user_state/session_state.py
st_user_state/state_proxy.py
st_user_state/states.py
st_user_state-0.3.0.dist-info/METADATA
st_user_state-0.3.0.dist-info/WHEEL
st_user_state-0.3.0.dist-info/RECORD
