Metadata-Version: 2.3
Name: st-user-state
Version: 0.3.0
Summary: Persistent sessions for Streamlit.
Requires-Python: >=3.11,<4.0
Classifier: Programming Language :: Python :: 3
Classifier: Programming Language :: Python :: 3.11
Classifier: Programming Language :: Python :: 3.12
Classifier: Programming Language :: Python :: 3.13
Requires-Dist: streamlit (>=1.41.0,<2.0.0)
